MANIFEST.in
README.txt
setup.py
sancta_article/__init__.py
sancta_article/admin.py
sancta_article/models.py
sancta_article/views.py
sancta_article.egg-info/PKG-INFO
sancta_article.egg-info/SOURCES.txt
sancta_article.egg-info/dependency_links.txt
sancta_article.egg-info/top_level.txt