Metadata-Version: 1.1
Name: sancta-article
Version: 0.0.2
Summary: article tools
Home-page: https://github.com/Ravall/sancta_article.git
Author: Valeriy Semenov
Author-email: valery.ravall@gmail.com
License: MIT License
Download-URL: https://github.com/Ravall/sancta_article/tarball/master
Platform: UNKNOWN
Classifier: Environment :: Web Environment
Classifier: Intended Audience :: Developers
Classifier: Programming Language :: Python
Requires: python (>= 2.5)
